orichain/__init__.py
orichain/embeddings/__init__.py
orichain/embeddings/awsbedrock_embeddings.py
orichain/embeddings/azureopenai_embeddings.py
orichain/embeddings/gcp_gemini_embeddings.py
orichain/embeddings/gcp_vertex_embeddings.py
orichain/embeddings/openai_embeddings.py
orichain/embeddings/stransformers_embeddings.py
orichain/embeddings/togetherai_embeddings.py
orichain/knowledge_base/__init__.py
orichain/knowledge_base/chromadb_knowledgebase.py
orichain/knowledge_base/pinecone_knowledgbase.py
orichain/lang_detect/__init__.py
orichain/llm/__init__.py
orichain/llm/anthropic_llm.py
orichain/llm/anthropicbedrock_llm.py
orichain/llm/awsbedrock_llm.py
orichain/llm/azureopenai_llm.py
orichain/llm/gcp_gemini_llm.py
orichain/llm/gcp_vertex_llm.py
orichain/llm/openai_llm.py
orichain/llm/togetherai_llm.py
orichain-2.6.0.dist-info/METADATA
orichain-2.6.0.dist-info/WHEEL
orichain-2.6.0.dist-info/licenses/LICENSE
orichain-2.6.0.dist-info/RECORD
