Metadata-Version: 2.4
Name: orichain
Version: 2.6.0
Summary: Python lib created only for RAG related text based enterprise solutions
Project-URL: Homepage, https://github.com/OriserveAI/orichain
Project-URL: Repository, https://github.com/OriserveAI/orichain
Author-email: apoorv-singh-107 <apoorv.singh@oriserve.com>, apoorv-singh-107 <apoorvsingh.work@gmail.com>, shubham-maindola <shubham.maindola@oriserve.com>, shubham-maindola <smaindola90@oriserve.com>, Rishu-Ranjan <rishu.ranjan@oriserve.com>, Rishu-Ranjan <almaktashi@gmail.com>
License:                                  Apache License
License-File: LICENSE
Requires-Python: >=3.10.13
Requires-Dist: anthropic==0.45.2
Requires-Dist: art==6.4
Requires-Dist: boto3==1.38.5
Requires-Dist: botocore==1.38.5
Requires-Dist: chromadb==0.6.3
Requires-Dist: fastapi==0.115.8
Requires-Dist: google-genai==1.20.0
Requires-Dist: openai==1.62.0
Requires-Dist: pinecone[grpc]==6.0.1
Requires-Dist: pysqlite3-binary==0.5.4; sys_platform == 'linux'
Requires-Dist: tiktoken==0.8.0
Requires-Dist: together==1.5.25
Provides-Extra: lingua-language-detector
Requires-Dist: lingua-language-detector==2.1.0; extra == 'lingua-language-detector'
Provides-Extra: sentence-transformers
Requires-Dist: sentence-transformers==3.4.1; extra == 'sentence-transformers'
